figipy/__init__.py
figipy/core.py
figipy/error.py
figipy/range.py
figipy/resources/__init__.py
figipy-0.1.3.dist-info/WHEEL
figipy-0.1.3.dist-info/METADATA
figipy-0.1.3.dist-info/RECORD
