Metadata-Version: 2.1
Name: figipy
Version: 0.1.3
Summary: Unofficial Python API for OpenFIGI (https://www.openfigi.com/)
Home-page: https://github.com/ThomasKluiters/figipy
Author: Thomas Kluiters
Author-email: thomas.kluiters@gmail.com
Requires-Python: >=3.8.6,<4.0.0
Classifier: Programming Language :: Python :: 3
Classifier: Programming Language :: Python :: 3.9
Requires-Dist: black (>=20.8b1,<21.0)
Requires-Dist: requests (>=2.25.0,<3.0.0)
